pydoll/__init__.py
pydoll/browser/__init__.py
pydoll/browser/chromium/__init__.py
pydoll/browser/chromium/base.py
pydoll/browser/chromium/chrome.py
pydoll/browser/chromium/edge.py
pydoll/browser/interfaces.py
pydoll/browser/managers/__init__.py
pydoll/browser/managers/browser_options_manager.py
pydoll/browser/managers/browser_process_manager.py
pydoll/browser/managers/proxy_manager.py
pydoll/browser/managers/temp_dir_manager.py
pydoll/browser/options.py
pydoll/browser/requests/__init__.py
pydoll/browser/requests/request.py
pydoll/browser/requests/response.py
pydoll/browser/tab.py
pydoll/commands/__init__.py
pydoll/commands/browser_commands.py
pydoll/commands/dom_commands.py
pydoll/commands/fetch_commands.py
pydoll/commands/input_commands.py
pydoll/commands/network_commands.py
pydoll/commands/page_commands.py
pydoll/commands/runtime_commands.py
pydoll/commands/storage_commands.py
pydoll/commands/target_commands.py
pydoll/connection/__init__.py
pydoll/connection/connection_handler.py
pydoll/connection/managers/__init__.py
pydoll/connection/managers/commands_manager.py
pydoll/connection/managers/events_manager.py
pydoll/constants.py
pydoll/decorators.py
pydoll/elements/__init__.py
pydoll/elements/mixins/__init__.py
pydoll/elements/mixins/find_elements_mixin.py
pydoll/elements/web_element.py
pydoll/exceptions.py
pydoll/interactions/__init__.py
pydoll/interactions/keyboard.py
pydoll/interactions/scroll.py
pydoll/protocol/__init__.py
pydoll/protocol/base.py
pydoll/protocol/browser/__init__.py
pydoll/protocol/browser/events.py
pydoll/protocol/browser/methods.py
pydoll/protocol/browser/types.py
pydoll/protocol/debugger/types.py
pydoll/protocol/dom/__init__.py
pydoll/protocol/dom/events.py
pydoll/protocol/dom/methods.py
pydoll/protocol/dom/types.py
pydoll/protocol/emulation/types.py
pydoll/protocol/fetch/__init__.py
pydoll/protocol/fetch/events.py
pydoll/protocol/fetch/methods.py
pydoll/protocol/fetch/types.py
pydoll/protocol/input/__init__.py
pydoll_python-2.12.1.dist-info/METADATA
pydoll_python-2.12.1.dist-info/WHEEL
pydoll_python-2.12.1.dist-info/licenses/LICENSE
pydoll_python-2.12.1.dist-info/RECORD
