Metadata-Version: 2.4
Name: pydoll-python
Version: 2.12.1
Summary: Pydoll is a library for automating chromium-based browsers without a WebDriver, offering realistic interactions.
License-File: LICENSE
Author: Thalison Fernandes
Author-email: thalissfernandes99@gmail.com
Requires-Python: >=3.10,<4.0
Classifier: Programming Language :: Python :: 3
Classifier: Programming Language :: Python :: 3.10
Classifier: Programming Language :: Python :: 3.11
Classifier: Programming Language :: Python :: 3.12
Classifier: Programming Language :: Python :: 3.13
Classifier: Programming Language :: Python :: 3.14
Requires-Dist: aiofiles (>=25.1.0,<26.0.0)
Requires-Dist: aiohttp (>=3.9.5,<4.0.0)
Requires-Dist: typing_extensions (>=4.14.0,<5.0.0)
Requires-Dist: websockets (>=14,<15)
